metaibricks/__init__.py
metaibricks/__main__.py
metaibricks/base.py
metaibricks/extraction/__init__.py
metaibricks/extraction/base.py
metaibricks/extraction/ftp.py
metaibricks/pipeline/__init__.py
metaibricks/pipeline/pipeline.py
metaibricks/settings/__init__.py
metaibricks/settings/cli.py
metaibricks/settings/logger.py
metaibricks/settings/settings.py
metaibricks-0.1.dist-info/METADATA
metaibricks-0.1.dist-info/WHEEL
metaibricks-0.1.dist-info/top_level.txt
metaibricks-0.1.dist-info/RECORD
