Metadata-Version: 2.1
Name: metaibricks
Version: 0.1
Summary: Met-AI-Bricks : Meteorological AI Bricks
Home-page: http://gitlab.meteo.fr/deep_learning/ai-lab-tools/met-ai-bricks
Author: LabIA-MF
Author-email: lab_ia@meteo.fr
License: UNKNOWN
Platform: UNKNOWN
